sbcommons/__init__.py
sbcommons/utils.py
sbcommons/adp/__init__.py
sbcommons/adp/client.py
sbcommons/aws/__init__.py
sbcommons/aws/dms.py
sbcommons/aws/lambdas.py
sbcommons/aws/redshift.py
sbcommons/aws/s3.py
sbcommons/aws/secrets.py
sbcommons/aws/sns.py
sbcommons/crm/__init__.py
sbcommons/crm/client.py
sbcommons/crm/factories.py
sbcommons/crm/parser.py
sbcommons/crm/klaviyo/__init__.py
sbcommons/crm/klaviyo/campaign.py
sbcommons/crm/klaviyo/client.py
sbcommons/crm/klaviyo/event.py
sbcommons/crm/klaviyo/metric.py
sbcommons/crm/klaviyo/parser.py
sbcommons/crm/klaviyo/url.py
sbcommons/crm/symplify/__init__.py
sbcommons/crm/symplify/client.py
sbcommons/crm/symplify/parser.py
sbcommons/extract_utils/__init__.py
sbcommons/extract_utils/utils.py
sbcommons/logging/__init__.py
sbcommons/logging/lambda_logger.py
sbcommons/logging/rotating_file_handler.py
sbcommons/messaging/__init__.py
sbcommons/messaging/webhooks.py
sbcommons/parse_utils/__init__.py
sbcommons/slack/__init__.py
sbcommons/slack/slack.py
sbcommons/teams/__init__.py
sbcommons/teams/teams.py
tests/__init__.py
tests/test_utils.py
tests/extract_utils/__init__.py
tests/extract_utils/test_utils.py
tests/teams/__init__.py
tests/teams/test_teams.py
sbcommons-1.2.1.dist-info/LICENSE
sbcommons-1.2.1.dist-info/METADATA
sbcommons-1.2.1.dist-info/WHEEL
sbcommons-1.2.1.dist-info/top_level.txt
sbcommons-1.2.1.dist-info/RECORD
