Metadata-Version: 2.1
Name: sbcommons
Version: 1.2.1
Summary: Packages shared between several Data related systems in Haypp Group
Home-page: https://github.com/Snusbolaget
Author: Haypp Group
Author-email: data@hayppgroup.com
Classifier: Programming Language :: Python :: 3.9
Classifier: License :: OSI Approved :: MIT License
Classifier: Operating System :: OS Independent
License-File: LICENSE
Requires-Dist: boto3 (>=1.24.35)
Requires-Dist: botocore (>=1.27.35)
Requires-Dist: urllib3 (>=1.26.10)
Requires-Dist: requests (>=2.28.1)
Requires-Dist: aws-secretsmanager-caching (>=1.1.1.5)
